hexpex/__init__.py
hexpex/hex.py
hexpex-0.2.3.dist-info/LICENSE
hexpex-0.2.3.dist-info/METADATA
hexpex-0.2.3.dist-info/WHEEL
hexpex-0.2.3.dist-info/RECORD
