Metadata-Version: 2.1
Name: hexpex
Version: 0.2.3
Summary: A type-hinted, object-oriented Python implementation for working with hex grids
Home-page: https://github.com/solbero/hexpex
License: GPLv3
Author: solbero
Author-email: njord.solberg@gmail.com
Requires-Python: >=3.9,<4.0
Classifier: License :: Other/Proprietary License
Classifier: Programming Language :: Python :: 3
Classifier: Programming Language :: Python :: 3.9
Classifier: Programming Language :: Python :: 3.10
Classifier: Programming Language :: Python :: 3.11
Project-URL: Repository, https://github.com/solbero/hexpex
